easy_tcp_python2_3/__init__.py
easy_tcp_python2_3/socket_utils.py
easy_tcp_python2_3-0.0.1.0.dist-info/METADATA
easy_tcp_python2_3-0.0.1.0.dist-info/WHEEL
easy_tcp_python2_3-0.0.1.0.dist-info/top_level.txt
easy_tcp_python2_3-0.0.1.0.dist-info/RECORD
