Metadata-Version: 2.1
Name: easy-tcp-python2-3
Version: 0.0.1.0
Summary: easy socket programming between python 2 and 3 without compatibility issues
Home-page: https://github.com/SeungBack/easy_tcp_python2_3
Author: Seunghyeok Back
Author-email: shback@gist.ac.kr
License: UNKNOWN
Platform: UNKNOWN
Classifier: Programming Language :: Python :: 2.7
Classifier: Programming Language :: Python :: 3.7
Classifier: Programming Language :: Python :: 3.8
Classifier: Programming Language :: Python :: 3.9
Classifier: License :: OSI Approved :: MIT License
Classifier: Operating System :: OS Independent
